quadratic_sieve/__init__.py
quadratic_sieve/base.py
quadratic_sieve/fast_gauss.py
quadratic_sieve/primes.py
quadratic_sieve/primes.txt
quadratic_sieve/quadratic_sieve.py
quadratic_sieve-0.1.2.data/scripts/quadratic_sieve
quadratic_sieve-0.1.2.dist-info/LICENSE
quadratic_sieve-0.1.2.dist-info/METADATA
quadratic_sieve-0.1.2.dist-info/WHEEL
quadratic_sieve-0.1.2.dist-info/top_level.txt
quadratic_sieve-0.1.2.dist-info/RECORD
