Metadata-Version: 2.1
Name: quadratic-sieve
Version: 0.1.2
Summary: A basic implementation of the quadratic sieve factorization.
Home-page: https://github.com/cocojambo320/quadratic-sieve
Author: Mikolaj Sawicki
Author-email: msawicki9999@gmail.com
License: GNU General Public License v3.0
Download-URL: https://github.com/cocojambo320/quadratic-sieve
Keywords: factorization,prime,number,theory,quadratic,sieve
Platform: UNKNOWN
Requires-Python: >=3.7
Requires-Dist: numpy
